mongu.py
setup.py
mongu.egg-info/PKG-INFO
mongu.egg-info/SOURCES.txt
mongu.egg-info/dependency_links.txt
mongu.egg-info/requires.txt
mongu.egg-info/top_level.txt