Metadata-Version: 1.0
Name: mongu
Version: 0.4.4
Summary: Yet another Python Object-Document Mapper on top of PyMongo.
Home-page: http://github.com/tevino/mongu
Author: Tevin Zhang
Author-email: mail2tevin@gmail.com
License: MIT
Platform: any
